{
  "description": "GroupSubject holds detailed information for group-kind subject.",
  "properties": {
    "name": {
      "description": "name is the user group that matches, or \"*\" to match all user groups. See https://github.com/kubernetes/apiserver/blob/master/pkg/authentication/user/user.go for some well-known group names. Required.",
      "type": [
        "string",
        "null"
      ]
    }
  },
  "required": [
    "name"
  ],
  "type": "object",
  "$schema": "http://json-schema.org/schema#"
}