{
  "description": "DeploymentStrategy describes how to replace existing pods with new ones.",
  "properties": {
    "rollingUpdate": {
      "description": "Spec to control the desired behavior of rolling update.",
      "properties": {
        "maxSurge": {
          "oneOf": [
            {
              "type": [
                "string",
                "null"
              ]
            },
            {
              "type": [
                "integer",
                "null"
              ]
            }
          ]
        },
        "maxUnavailable": {
          "oneOf": [
            {
              "type": [
                "string",
                "null"
              ]
            },
            {
              "type": [
                "integer",
                "null"
              ]
            }
          ]
        }
      },
      "type": [
        "object",
        "null"
      ]
    },
    "type": {
      "description": "Type of deployment. Can be \"Recreate\" or \"RollingUpdate\". Default is RollingUpdate.",
      "type": [
        "string",
        "null"
      ]
    }
  },
  "type": "object",
  "$schema": "http://json-schema.org/schema#"
}