{
  "description": "APIServiceStatus contains derived information about an API server",
  "properties": {
    "conditions": {
      "description": "Current service state of apiService.",
      "items": {
        "description": "APIServiceCondition describes the state of an APIService at a particular point",
        "properties": {
          "lastTransitionTime": {
            "description": "Time is a wrapper around time.Time which supports correct marshaling to YAML and JSON.  Wrappers are provided for many of the factory methods that the time package offers.",
            "format": "date-time",
            "type": [
              "string",
              "null"
            ]
          },
          "message": {
            "description": "Human-readable message indicating details about last transition.",
            "type": [
              "string",
              "null"
            ]
          },
          "reason": {
            "description": "Unique, one-word, CamelCase reason for the condition's last transition.",
            "type": [
              "string",
              "null"
            ]
          },
          "status": {
            "description": "Status is the status of the condition. Can be True, False, Unknown.",
            "type": "string"
          },
          "type": {
            "description": "Type is the type of the condition.",
            "type": "string"
          }
        },
        "required": [
          "type",
          "status"
        ],
        "type": [
          "object",
          "null"
        ]
      },
      "type": [
        "array",
        "null"
      ],
      "x-kubernetes-patch-merge-key": "type",
      "x-kubernetes-patch-strategy": "merge"
    }
  },
  "type": "object",
  "$schema": "http://json-schema.org/schema#"
}